flowpyter_task-1.3.4.dist-info/licenses/LICENSE
flowpytertask/__init__.py
flowpytertask/_version.py
flowpytertask/flowpytertask.py
flowpytertask/plugins/__init__.py
flowpytertask/plugins/base64_jinja.py
flowpyter_task-1.3.4.dist-info/METADATA
flowpyter_task-1.3.4.dist-info/WHEEL
flowpyter_task-1.3.4.dist-info/entry_points.txt
flowpyter_task-1.3.4.dist-info/top_level.txt
flowpyter_task-1.3.4.dist-info/zip-safe
flowpyter_task-1.3.4.dist-info/RECORD
