Metadata-Version: 2.4
Name: flowpyter-task
Version: 1.3.4
Home-page: https://github.com/Flowminder/flowpyter-task
Author: Flowminder Foundation
Author-email: flowkit@flowminder.org
Keywords: mobile telecommunications analysis
Platform: MacOS X
Platform: Linux
Classifier: License :: OSI Approved :: Mozilla Public License 2.0 (MPL 2.0)
Classifier: Development Status :: 4 - Beta
Classifier: Programming Language :: Python :: 3.10
Classifier: Natural Language :: English
Classifier: Operating System :: MacOS :: MacOS X
Classifier: Operating System :: POSIX
Classifier: Operating System :: POSIX :: Linux
License-File: LICENSE
Requires-Dist: apache_airflow<3,>=2.9.2
Requires-Dist: apache-airflow-providers-docker
Requires-Dist: psycopg2-binary
Provides-Extra: dev
Requires-Dist: versioneer; extra == "dev"
Requires-Dist: black; extra == "dev"
Provides-Extra: test
Requires-Dist: pytest; extra == "test"
Requires-Dist: approvaltests; extra == "test"
Requires-Dist: pytest-docker; extra == "test"
Requires-Dist: flowkit_jwt_generator; extra == "test"
Dynamic: author
Dynamic: author-email
Dynamic: classifier
Dynamic: description
Dynamic: description-content-type
Dynamic: home-page
Dynamic: keywords
Dynamic: license-file
Dynamic: platform
Dynamic: provides-extra
Dynamic: requires-dist
